pycocoedit/__init__.py
pycocoedit/objectdetection/__init__.py
pycocoedit/objectdetection/data.py
pycocoedit/objectdetection/filter.py
pycocoedit-0.0.1.dist-info/LICENSE
pycocoedit-0.0.1.dist-info/METADATA
pycocoedit-0.0.1.dist-info/WHEEL
pycocoedit-0.0.1.dist-info/RECORD
