Metadata-Version: 2.3
Name: pycocoedit
Version: 0.0.1
Summary: Advanced editing tools for COCO dataset annotations
License: Apache-2.0
Keywords: COCO,annotation,dataset,filter,computer vision
Author: hachimada
Author-email: 60519909+hachimada@users.noreply.github.com
Requires-Python: >=3.10,<4.0
Classifier: Development Status :: 4 - Beta
Classifier: Intended Audience :: Developers
Classifier: License :: OSI Approved :: Apache Software License
Classifier: Programming Language :: Python :: 3
Classifier: Programming Language :: Python :: 3.10
Classifier: Programming Language :: Python :: 3.11
Classifier: Programming Language :: Python :: 3.12
Classifier: Programming Language :: Python :: 3.13
Classifier: Programming Language :: Python :: 3 :: Only
Classifier: Topic :: Scientific/Engineering :: Image Recognition
Requires-Dist: typing-extensions (>=4.13.2,<5.0.0)
Project-URL: Bug Tracker, https://github.com/Nao-Y1996/pycocoedit/issues
Project-URL: homepage, https://github.com/Nao-Y1996/pycocoedit
Project-URL: repository, https://github.com/Nao-Y1996/pycocoedit
